pyskel2graph/__init__.py
pyskel2graph/api.py
pyskel2graph/degree.py
pyskel2graph/graph.py
pyskel2graph/io.py
pyskel2graph/metrics.py
pyskel2graph/pruning.py
pyskel2graph/vis.py
pyskel2graph-0.1.0.dist-info/licenses/LICENSE
pyskel2graph-0.1.0.dist-info/METADATA
pyskel2graph-0.1.0.dist-info/WHEEL
pyskel2graph-0.1.0.dist-info/top_level.txt
pyskel2graph-0.1.0.dist-info/RECORD
