Metadata-Version: 2.4
Name: pyskel2graph
Version: 0.1.0
Summary: Convert the Skeleton to a Graph using Python.
Home-page: https://https://github.com/SummerColdWind
Author: Qincheng Qiao
Author-email: jugking6688@gmail.com
Classifier: Development Status :: 1 - Planning
Classifier: License :: OSI Approved :: GNU General Public License v3 (GPLv3)
Classifier: Topic :: Scientific/Engineering :: Medical Science Apps.
Requires-Python: >=3.10
License-File: LICENSE
Requires-Dist: matplotlib
Requires-Dist: numpy<2.0.0
Requires-Dist: scikit-image
Requires-Dist: networkx
Requires-Dist: scipy
Requires-Dist: opencv-python
Dynamic: author
Dynamic: author-email
Dynamic: classifier
Dynamic: description
Dynamic: description-content-type
Dynamic: home-page
Dynamic: license-file
Dynamic: requires-dist
Dynamic: requires-python
Dynamic: summary
